{{define "config"}}{
    "key": "bb-sonar-stats",
    "name": "Bitbucket sonar stats",
    "description": "Pass sonar project stats to bitbucket repo.",
    "vendor": {
        "name": "1node",
        "url": "https://1node.xyz"
    },
    "baseUrl": "{{.BaseUrl}}",
    "authentication": {
        "type": "jwt"
    },
    "lifecycle": {
        "installed": "/installed",
        "uninstalled": "/uninstalled"
    },
    "modules": {
        "oauthConsumer": {
            "clientId": "{{.ConsumerKey}}"
        },
        "webhooks": [
            {
                "event": "*",
                "url": "/webhook"
            }
        ],
        "webPanel": [
            {
                "url": "/stats?repoPath={repo_path}",
                "name": {
                    "value": "Sonarqube project statistics."
                },
                "location": "org.bitbucket.repository.overview.informationPanel",
                "key": "sonar-stats-panel"
            }
        ]
    },
    "scopes": ["account", "repository"],
    "contexts": ["account"]
}
{{end}}
